[
  {
    "id": "110153902206014478",
    "created_at": "2023-04-06T21:05:58.179Z",
    "in_reply_to_id": null,
    "in_reply_to_account_id": null,
    "sensitive": false,
    "spoiler_text": "",
    "visibility": "public",
    "language": "en",
    "uri": "https://botsin.space/users/ngstargetbot/statuses/110153902206014478",
    "url": "https://botsin.space/@ngstargetbot/110153902206014478",
    "replies_count": 0,
    "reblogs_count": 0,
    "favourites_count": 0,
    "edited_at": null,
    "content": "<p>Harukotan Devastators</p><p>Malevolent Granmizer<br />Malevolent Vardias<br />Malevolent Pangolan<br />Malevolent Ard Banser<br />Malevolent Volgbear</p>",
    "reblog": null,
    "application": {
      "name": "CheapBotsTootSweet",
      "website": null
    },
    "account": {
      "id": "109815966467481665",
      "username": "ngstargetbot",
      "acct": "ngstargetbot",
      "display_name": "NGS Content BOT",
      "locked": false,
      "bot": true,
      "discoverable": false,
      "group": false,
      "created_at": "2023-02-06T00:00:00.000Z",
      "note": "<p>TRIAL START</p><p>Automated random toots twice per hour<br />Autoreplies to mentions/replies w/&quot;builds&quot;</p>",
      "url": "https://botsin.space/@ngstargetbot",
      "avatar": "https://files.botsin.space/accounts/avatars/109/815/966/467/481/665/original/aa0b33e3055080b3.png",
      "avatar_static": "https://files.botsin.space/accounts/avatars/109/815/966/467/481/665/original/aa0b33e3055080b3.png",
      "header": "https://files.botsin.space/accounts/headers/109/815/966/467/481/665/original/b53d72ec0b30c92a.jpg",
      "header_static": "https://files.botsin.space/accounts/headers/109/815/966/467/481/665/original/b53d72ec0b30c92a.jpg",
      "followers_count": 5,
      "following_count": 0,
      "statuses_count": 2727,
      "last_status_at": "2023-04-06",
      "noindex": true,
      "emojis": [],
      "roles": [],
      "fields": []
    },
    "media_attachments": [],
    "mentions": [],
    "tags": [],
    "emojis": [],
    "card": null,
    "poll": null
  },
  {
    "id": "110153784167913759",
    "created_at": "2023-04-06T20:35:57.062Z",
    "in_reply_to_id": null,
    "in_reply_to_account_id": null,
    "sensitive": false,
    "spoiler_text": "",
    "visibility": "public",
    "language": "en",
    "uri": "https://botsin.space/users/ngstargetbot/statuses/110153784167913759",
    "url": "https://botsin.space/@ngstargetbot/110153784167913759",
    "replies_count": 0,
    "reblogs_count": 0,
    "favourites_count": 0,
    "edited_at": null,
    "content": "<p>Lv.3 Flamm Frango<br />Resists: Dying</p>",
    "reblog": null,
    "application": {
      "name": "CheapBotsTootSweet",
      "website": null
    },
    "account": {
      "id": "109815966467481665",
      "username": "ngstargetbot",
      "acct": "ngstargetbot",
      "display_name": "NGS Content BOT",
      "locked": false,
      "bot": true,
      "discoverable": false,
      "group": false,
      "created_at": "2023-02-06T00:00:00.000Z",
      "note": "<p>TRIAL START</p><p>Automated random toots twice per hour<br />Autoreplies to mentions/replies w/&quot;builds&quot;</p>",
      "url": "https://botsin.space/@ngstargetbot",
      "avatar": "https://files.botsin.space/accounts/avatars/109/815/966/467/481/665/original/aa0b33e3055080b3.png",
      "avatar_static": "https://files.botsin.space/accounts/avatars/109/815/966/467/481/665/original/aa0b33e3055080b3.png",
      "header": "https://files.botsin.space/accounts/headers/109/815/966/467/481/665/original/b53d72ec0b30c92a.jpg",
      "header_static": "https://files.botsin.space/accounts/headers/109/815/966/467/481/665/original/b53d72ec0b30c92a.jpg",
      "followers_count": 5,
      "following_count": 0,
      "statuses_count": 2727,
      "last_status_at": "2023-04-06",
      "noindex": true,
      "emojis": [],
      "roles": [],
      "fields": []
    },
    "media_attachments": [],
    "mentions": [],
    "tags": [],
    "emojis": [],
    "card": null,
    "poll": null
  },
  {
    "id": "110153753135390647",
    "created_at": "2023-04-06T20:28:03.538Z",
    "in_reply_to_id": null,
    "in_reply_to_account_id": null,
    "sensitive": false,
    "spoiler_text": "",
    "visibility": "public",
    "language": "en",
    "uri": "https://botsin.space/users/ngstargetbot/statuses/110153753135390647",
    "url": "https://botsin.space/@ngstargetbot/110153753135390647",
    "replies_count": 0,
    "reblogs_count": 0,
    "favourites_count": 0,
    "edited_at": null,
    "content": "<p>I really enjoy playing the Techter class, but I feel it&#39;s too reliant on Jet Intensity and I feel really weak while it&#39;s on cooldown.</p>",
    "reblog": null,
    "application": {
      "name": "CheapBotsTootSweet",
      "website": null
    },
    "account": {
      "id": "109815966467481665",
      "username": "ngstargetbot",
      "acct": "ngstargetbot",
      "display_name": "NGS Content BOT",
      "locked": false,
      "bot": true,
      "discoverable": false,
      "group": false,
      "created_at": "2023-02-06T00:00:00.000Z",
      "note": "<p>TRIAL START</p><p>Automated random toots twice per hour<br />Autoreplies to mentions/replies w/&quot;builds&quot;</p>",
      "url": "https://botsin.space/@ngstargetbot",
      "avatar": "https://files.botsin.space/accounts/avatars/109/815/966/467/481/665/original/aa0b33e3055080b3.png",
      "avatar_static": "https://files.botsin.space/accounts/avatars/109/815/966/467/481/665/original/aa0b33e3055080b3.png",
      "header": "https://files.botsin.space/accounts/headers/109/815/966/467/481/665/original/b53d72ec0b30c92a.jpg",
      "header_static": "https://files.botsin.space/accounts/headers/109/815/966/467/481/665/original/b53d72ec0b30c92a.jpg",
      "followers_count": 5,
      "following_count": 0,
      "statuses_count": 2727,
      "last_status_at": "2023-04-06",
      "noindex": true,
      "emojis": [],
      "roles": [],
      "fields": []
    },
    "media_attachments": [
      {
        "id": "110153753124745583",
        "type": "image",
        "url": "https://files.botsin.space/media_attachments/files/110/153/753/124/745/583/original/f639e2a8cc955d7c.png",
        "preview_url": "https://files.botsin.space/media_attachments/files/110/153/753/124/745/583/small/f639e2a8cc955d7c.png",
        "remote_url": null,
        "preview_remote_url": null,
        "text_url": null,
        "meta": {
          "original": {
            "width": 1072,
            "height": 603,
            "size": "1072x603",
            "aspect": 1.7777777777777777
          },
          "small": {
            "width": 640,
            "height": 360,
            "size": "640x360",
            "aspect": 1.7777777777777777
          }
        },
        "description": null,
        "blurhash": "UWD9-h?bIUIo~q%gM{M{V?WBoeRk4.IUxus:"
      }
    ],
    "mentions": [],
    "tags": [],
    "emojis": [],
    "card": null,
    "poll": null
  },
  {
    "id": "110153739745382292",
    "created_at": "2023-04-06T20:24:39.225Z",
    "in_reply_to_id": null,
    "in_reply_to_account_id": null,
    "sensitive": false,
    "spoiler_text": "",
    "visibility": "public",
    "language": "en",
    "uri": "https://botsin.space/users/ngstargetbot/statuses/110153739745382292",
    "url": "https://botsin.space/@ngstargetbot/110153739745382292",
    "replies_count": 0,
    "reblogs_count": 0,
    "favourites_count": 0,
    "edited_at": null,
    "content": "<p>Cannonball Brawl</p><p>Wave: 9<br />Cannon Balls in play: 1<br />Targets Remaining: 7</p><p>Until Wave end: 7:35</p><p>Score: 7157788</p>",
    "reblog": null,
    "application": {
      "name": "CheapBotsTootSweet",
      "website": null
    },
    "account": {
      "id": "109815966467481665",
      "username": "ngstargetbot",
      "acct": "ngstargetbot",
      "display_name": "NGS Content BOT",
      "locked": false,
      "bot": true,
      "discoverable": false,
      "group": false,
      "created_at": "2023-02-06T00:00:00.000Z",
      "note": "<p>TRIAL START</p><p>Automated random toots twice per hour<br />Autoreplies to mentions/replies w/&quot;builds&quot;</p>",
      "url": "https://botsin.space/@ngstargetbot",
      "avatar": "https://files.botsin.space/accounts/avatars/109/815/966/467/481/665/original/aa0b33e3055080b3.png",
      "avatar_static": "https://files.botsin.space/accounts/avatars/109/815/966/467/481/665/original/aa0b33e3055080b3.png",
      "header": "https://files.botsin.space/accounts/headers/109/815/966/467/481/665/original/b53d72ec0b30c92a.jpg",
      "header_static": "https://files.botsin.space/accounts/headers/109/815/966/467/481/665/original/b53d72ec0b30c92a.jpg",
      "followers_count": 5,
      "following_count": 0,
      "statuses_count": 2727,
      "last_status_at": "2023-04-06",
      "noindex": true,
      "emojis": [],
      "roles": [],
      "fields": []
    },
    "media_attachments": [],
    "mentions": [],
    "tags": [],
    "emojis": [],
    "card": null,
    "poll": null
  },
  {
    "id": "110153690186733116",
    "created_at": "2023-04-06T20:12:03.015Z",
    "in_reply_to_id": null,
    "in_reply_to_account_id": null,
    "sensitive": false,
    "spoiler_text": "",
    "visibility": "public",
    "language": "en",
    "uri": "https://botsin.space/users/ngstargetbot/statuses/110153690186733116",
    "url": "https://botsin.space/@ngstargetbot/110153690186733116",
    "replies_count": 0,
    "reblogs_count": 0,
    "favourites_count": 0,
    "edited_at": null,
    "content": "<p>By learning War Cry Short Cycle, you reduce the duration of the skill while also reducing its cooldown, allowing you to use it more often.</p>",
    "reblog": null,
    "application": {
      "name": "CheapBotsTootSweet",
      "website": null
    },
    "account": {
      "id": "109815966467481665",
      "username": "ngstargetbot",
      "acct": "ngstargetbot",
      "display_name": "NGS Content BOT",
      "locked": false,
      "bot": true,
      "discoverable": false,
      "group": false,
      "created_at": "2023-02-06T00:00:00.000Z",
      "note": "<p>TRIAL START</p><p>Automated random toots twice per hour<br />Autoreplies to mentions/replies w/&quot;builds&quot;</p>",
      "url": "https://botsin.space/@ngstargetbot",
      "avatar": "https://files.botsin.space/accounts/avatars/109/815/966/467/481/665/original/aa0b33e3055080b3.png",
      "avatar_static": "https://files.botsin.space/accounts/avatars/109/815/966/467/481/665/original/aa0b33e3055080b3.png",
      "header": "https://files.botsin.space/accounts/headers/109/815/966/467/481/665/original/b53d72ec0b30c92a.jpg",
      "header_static": "https://files.botsin.space/accounts/headers/109/815/966/467/481/665/original/b53d72ec0b30c92a.jpg",
      "followers_count": 5,
      "following_count": 0,
      "statuses_count": 2727,
      "last_status_at": "2023-04-06",
      "noindex": true,
      "emojis": [],
      "roles": [],
      "fields": []
    },
    "media_attachments": [],
    "mentions": [],
    "tags": [],
    "emojis": [],
    "card": null,
    "poll": null
  },
  {
    "id": "110153666376113180",
    "created_at": "2023-04-06T20:05:59.710Z",
    "in_reply_to_id": null,
    "in_reply_to_account_id": null,
    "sensitive": false,
    "spoiler_text": "",
    "visibility": "public",
    "language": "en",
    "uri": "https://botsin.space/users/ngstargetbot/statuses/110153666376113180",
    "url": "https://botsin.space/@ngstargetbot/110153666376113180",
    "replies_count": 0,
    "reblogs_count": 0,
    "favourites_count": 0,
    "edited_at": null,
    "content": "<p>Lv.1 Dingale Lore<br />Weakness: Father</p>",
    "reblog": null,
    "application": {
      "name": "CheapBotsTootSweet",
      "website": null
    },
    "account": {
      "id": "109815966467481665",
      "username": "ngstargetbot",
      "acct": "ngstargetbot",
      "display_name": "NGS Content BOT",
      "locked": false,
      "bot": true,
      "discoverable": false,
      "group": false,
      "created_at": "2023-02-06T00:00:00.000Z",
      "note": "<p>TRIAL START</p><p>Automated random toots twice per hour<br />Autoreplies to mentions/replies w/&quot;builds&quot;</p>",
      "url": "https://botsin.space/@ngstargetbot",
      "avatar": "https://files.botsin.space/accounts/avatars/109/815/966/467/481/665/original/aa0b33e3055080b3.png",
      "avatar_static": "https://files.botsin.space/accounts/avatars/109/815/966/467/481/665/original/aa0b33e3055080b3.png",
      "header": "https://files.botsin.space/accounts/headers/109/815/966/467/481/665/original/b53d72ec0b30c92a.jpg",
      "header_static": "https://files.botsin.space/accounts/headers/109/815/966/467/481/665/original/b53d72ec0b30c92a.jpg",
      "followers_count": 5,
      "following_count": 0,
      "statuses_count": 2727,
      "last_status_at": "2023-04-06",
      "noindex": true,
      "emojis": [],
      "roles": [],
      "fields": []
    },
    "media_attachments": [],
    "mentions": [],
    "tags": [],
    "emojis": [],
    "card": null,
    "poll": null
  },
  {
    "id": "110153548276782589",
    "created_at": "2023-04-06T19:35:57.646Z",
    "in_reply_to_id": null,
    "in_reply_to_account_id": null,
    "sensitive": false,
    "spoiler_text": "",
    "visibility": "public",
    "language": "en",
    "uri": "https://botsin.space/users/ngstargetbot/statuses/110153548276782589",
    "url": "https://botsin.space/@ngstargetbot/110153548276782589",
    "replies_count": 0,
    "reblogs_count": 0,
    "favourites_count": 0,
    "edited_at": null,
    "content": "<p>Amduskia Devastators</p><p>Malevolent Ran<br />Malevolent Blaze Nogleth<br />Malevolent Xitre<br />Malevolent Volt Lemnas<br />Malevolent Aina</p>",
    "reblog": null,
    "application": {
      "name": "CheapBotsTootSweet",
      "website": null
    },
    "account": {
      "id": "109815966467481665",
      "username": "ngstargetbot",
      "acct": "ngstargetbot",
      "display_name": "NGS Content BOT",
      "locked": false,
      "bot": true,
      "discoverable": false,
      "group": false,
      "created_at": "2023-02-06T00:00:00.000Z",
      "note": "<p>TRIAL START</p><p>Automated random toots twice per hour<br />Autoreplies to mentions/replies w/&quot;builds&quot;</p>",
      "url": "https://botsin.space/@ngstargetbot",
      "avatar": "https://files.botsin.space/accounts/avatars/109/815/966/467/481/665/original/aa0b33e3055080b3.png",
      "avatar_static": "https://files.botsin.space/accounts/avatars/109/815/966/467/481/665/original/aa0b33e3055080b3.png",
      "header": "https://files.botsin.space/accounts/headers/109/815/966/467/481/665/original/b53d72ec0b30c92a.jpg",
      "header_static": "https://files.botsin.space/accounts/headers/109/815/966/467/481/665/original/b53d72ec0b30c92a.jpg",
      "followers_count": 5,
      "following_count": 0,
      "statuses_count": 2727,
      "last_status_at": "2023-04-06",
      "noindex": true,
      "emojis": [],
      "roles": [],
      "fields": []
    },
    "media_attachments": [],
    "mentions": [],
    "tags": [],
    "emojis": [],
    "card": null,
    "poll": null
  },
  {
    "id": "110153430338061395",
    "created_at": "2023-04-06T19:05:58.046Z",
    "in_reply_to_id": null,
    "in_reply_to_account_id": null,
    "sensitive": false,
    "spoiler_text": "",
    "visibility": "public",
    "language": "en",
    "uri": "https://botsin.space/users/ngstargetbot/statuses/110153430338061395",
    "url": "https://botsin.space/@ngstargetbot/110153430338061395",
    "replies_count": 0,
    "reblogs_count": 0,
    "favourites_count": 0,
    "edited_at": null,
    "content": "<p>Lv.31 Petalstorm Lumi Poloro Sword<br />Immune: Dark<br />Shield Weak Point: Attacks from below</p>",
    "reblog": null,
    "application": {
      "name": "CheapBotsTootSweet",
      "website": null
    },
    "account": {
      "id": "109815966467481665",
      "username": "ngstargetbot",
      "acct": "ngstargetbot",
      "display_name": "NGS Content BOT",
      "locked": false,
      "bot": true,
      "discoverable": false,
      "group": false,
      "created_at": "2023-02-06T00:00:00.000Z",
      "note": "<p>TRIAL START</p><p>Automated random toots twice per hour<br />Autoreplies to mentions/replies w/&quot;builds&quot;</p>",
      "url": "https://botsin.space/@ngstargetbot",
      "avatar": "https://files.botsin.space/accounts/avatars/109/815/966/467/481/665/original/aa0b33e3055080b3.png",
      "avatar_static": "https://files.botsin.space/accounts/avatars/109/815/966/467/481/665/original/aa0b33e3055080b3.png",
      "header": "https://files.botsin.space/accounts/headers/109/815/966/467/481/665/original/b53d72ec0b30c92a.jpg",
      "header_static": "https://files.botsin.space/accounts/headers/109/815/966/467/481/665/original/b53d72ec0b30c92a.jpg",
      "followers_count": 5,
      "following_count": 0,
      "statuses_count": 2727,
      "last_status_at": "2023-04-06",
      "noindex": true,
      "emojis": [],
      "roles": [],
      "fields": []
    },
    "media_attachments": [],
    "mentions": [],
    "tags": [],
    "emojis": [],
    "card": null,
    "poll": null
  },
  {
    "id": "110153312719327028",
    "created_at": "2023-04-06T18:36:03.323Z",
    "in_reply_to_id": null,
    "in_reply_to_account_id": null,
    "sensitive": false,
    "spoiler_text": "",
    "visibility": "public",
    "language": "en",
    "uri": "https://botsin.space/users/ngstargetbot/statuses/110153312719327028",
    "url": "https://botsin.space/@ngstargetbot/110153312719327028",
    "replies_count": 0,
    "reblogs_count": 0,
    "favourites_count": 0,
    "edited_at": null,
    "content": "<p>Daily: Defeat Gillnach Volore in Eastern Retem (1/9)</p>",
    "reblog": null,
    "application": {
      "name": "CheapBotsTootSweet",
      "website": null
    },
    "account": {
      "id": "109815966467481665",
      "username": "ngstargetbot",
      "acct": "ngstargetbot",
      "display_name": "NGS Content BOT",
      "locked": false,
      "bot": true,
      "discoverable": false,
      "group": false,
      "created_at": "2023-02-06T00:00:00.000Z",
      "note": "<p>TRIAL START</p><p>Automated random toots twice per hour<br />Autoreplies to mentions/replies w/&quot;builds&quot;</p>",
      "url": "https://botsin.space/@ngstargetbot",
      "avatar": "https://files.botsin.space/accounts/avatars/109/815/966/467/481/665/original/aa0b33e3055080b3.png",
      "avatar_static": "https://files.botsin.space/accounts/avatars/109/815/966/467/481/665/original/aa0b33e3055080b3.png",
      "header": "https://files.botsin.space/accounts/headers/109/815/966/467/481/665/original/b53d72ec0b30c92a.jpg",
      "header_static": "https://files.botsin.space/accounts/headers/109/815/966/467/481/665/original/b53d72ec0b30c92a.jpg",
      "followers_count": 5,
      "following_count": 0,
      "statuses_count": 2727,
      "last_status_at": "2023-04-06",
      "noindex": true,
      "emojis": [],
      "roles": [],
      "fields": []
    },
    "media_attachments": [],
    "mentions": [],
    "tags": [],
    "emojis": [],
    "card": null,
    "poll": null
  },
  {
    "id": "110153194417284118",
    "created_at": "2023-04-06T18:05:58.189Z",
    "in_reply_to_id": null,
    "in_reply_to_account_id": null,
    "sensitive": false,
    "spoiler_text": "",
    "visibility": "public",
    "language": "en",
    "uri": "https://botsin.space/users/ngstargetbot/statuses/110153194417284118",
    "url": "https://botsin.space/@ngstargetbot/110153194417284118",
    "replies_count": 0,
    "reblogs_count": 0,
    "favourites_count": 0,
    "edited_at": null,
    "content": "<p>C/Frostyl Soul IX</p>",
    "reblog": null,
    "application": {
      "name": "CheapBotsTootSweet",
      "website": null
    },
    "account": {
      "id": "109815966467481665",
      "username": "ngstargetbot",
      "acct": "ngstargetbot",
      "display_name": "NGS Content BOT",
      "locked": false,
      "bot": true,
      "discoverable": false,
      "group": false,
      "created_at": "2023-02-06T00:00:00.000Z",
      "note": "<p>TRIAL START</p><p>Automated random toots twice per hour<br />Autoreplies to mentions/replies w/&quot;builds&quot;</p>",
      "url": "https://botsin.space/@ngstargetbot",
      "avatar": "https://files.botsin.space/accounts/avatars/109/815/966/467/481/665/original/aa0b33e3055080b3.png",
      "avatar_static": "https://files.botsin.space/accounts/avatars/109/815/966/467/481/665/original/aa0b33e3055080b3.png",
      "header": "https://files.botsin.space/accounts/headers/109/815/966/467/481/665/original/b53d72ec0b30c92a.jpg",
      "header_static": "https://files.botsin.space/accounts/headers/109/815/966/467/481/665/original/b53d72ec0b30c92a.jpg",
      "followers_count": 5,
      "following_count": 0,
      "statuses_count": 2727,
      "last_status_at": "2023-04-06",
      "noindex": true,
      "emojis": [],
      "roles": [],
      "fields": []
    },
    "media_attachments": [],
    "mentions": [],
    "tags": [],
    "emojis": [],
    "card": null,
    "poll": null
  },
  {
    "id": "110153076974274764",
    "created_at": "2023-04-06T17:36:06.144Z",
    "in_reply_to_id": null,
    "in_reply_to_account_id": null,
    "sensitive": false,
    "spoiler_text": "",
    "visibility": "public",
    "language": "en",
    "uri": "https://botsin.space/users/ngstargetbot/statuses/110153076974274764",
    "url": "https://botsin.space/@ngstargetbot/110153076974274764",
    "replies_count": 0,
    "reblogs_count": 0,
    "favourites_count": 0,
    "edited_at": null,
    "content": "<p>Lv.7 Lumi Otarica<br />Immune: Gettemhult</p>",
    "reblog": null,
    "application": {
      "name": "CheapBotsTootSweet",
      "website": null
    },
    "account": {
      "id": "109815966467481665",
      "username": "ngstargetbot",
      "acct": "ngstargetbot",
      "display_name": "NGS Content BOT",
      "locked": false,
      "bot": true,
      "discoverable": false,
      "group": false,
      "created_at": "2023-02-06T00:00:00.000Z",
      "note": "<p>TRIAL START</p><p>Automated random toots twice per hour<br />Autoreplies to mentions/replies w/&quot;builds&quot;</p>",
      "url": "https://botsin.space/@ngstargetbot",
      "avatar": "https://files.botsin.space/accounts/avatars/109/815/966/467/481/665/original/aa0b33e3055080b3.png",
      "avatar_static": "https://files.botsin.space/accounts/avatars/109/815/966/467/481/665/original/aa0b33e3055080b3.png",
      "header": "https://files.botsin.space/accounts/headers/109/815/966/467/481/665/original/b53d72ec0b30c92a.jpg",
      "header_static": "https://files.botsin.space/accounts/headers/109/815/966/467/481/665/original/b53d72ec0b30c92a.jpg",
      "followers_count": 5,
      "following_count": 0,
      "statuses_count": 2727,
      "last_status_at": "2023-04-06",
      "noindex": true,
      "emojis": [],
      "roles": [],
      "fields": []
    },
    "media_attachments": [],
    "mentions": [],
    "tags": [],
    "emojis": [],
    "card": null,
    "poll": null
  },
  {
    "id": "110152958372461885",
    "created_at": "2023-04-06T17:05:56.422Z",
    "in_reply_to_id": null,
    "in_reply_to_account_id": null,
    "sensitive": false,
    "spoiler_text": "",
    "visibility": "public",
    "language": "en",
    "uri": "https://botsin.space/users/ngstargetbot/statuses/110152958372461885",
    "url": "https://botsin.space/@ngstargetbot/110152958372461885",
    "replies_count": 0,
    "reblogs_count": 0,
    "favourites_count": 0,
    "edited_at": null,
    "content": "<p>Lv.83 Bubble Snapper<br />Resists: Nighttime</p>",
    "reblog": null,
    "application": {
      "name": "CheapBotsTootSweet",
      "website": null
    },
    "account": {
      "id": "109815966467481665",
      "username": "ngstargetbot",
      "acct": "ngstargetbot",
      "display_name": "NGS Content BOT",
      "locked": false,
      "bot": true,
      "discoverable": false,
      "group": false,
      "created_at": "2023-02-06T00:00:00.000Z",
      "note": "<p>TRIAL START</p><p>Automated random toots twice per hour<br />Autoreplies to mentions/replies w/&quot;builds&quot;</p>",
      "url": "https://botsin.space/@ngstargetbot",
      "avatar": "https://files.botsin.space/accounts/avatars/109/815/966/467/481/665/original/aa0b33e3055080b3.png",
      "avatar_static": "https://files.botsin.space/accounts/avatars/109/815/966/467/481/665/original/aa0b33e3055080b3.png",
      "header": "https://files.botsin.space/accounts/headers/109/815/966/467/481/665/original/b53d72ec0b30c92a.jpg",
      "header_static": "https://files.botsin.space/accounts/headers/109/815/966/467/481/665/original/b53d72ec0b30c92a.jpg",
      "followers_count": 5,
      "following_count": 0,
      "statuses_count": 2727,
      "last_status_at": "2023-04-06",
      "noindex": true,
      "emojis": [],
      "roles": [],
      "fields": []
    },
    "media_attachments": [],
    "mentions": [],
    "tags": [],
    "emojis": [],
    "card": null,
    "poll": null
  },
  {
    "id": "110152840374663064",
    "created_at": "2023-04-06T16:35:55.918Z",
    "in_reply_to_id": null,
    "in_reply_to_account_id": null,
    "sensitive": false,
    "spoiler_text": "",
    "visibility": "public",
    "language": "en",
    "uri": "https://botsin.space/users/ngstargetbot/statuses/110152840374663064",
    "url": "https://botsin.space/@ngstargetbot/110152840374663064",
    "replies_count": 0,
    "reblogs_count": 0,
    "favourites_count": 0,
    "edited_at": null,
    "content": "<p>Manon says:</p><p>Run</p>",
    "reblog": null,
    "application": {
      "name": "CheapBotsTootSweet",
      "website": null
    },
    "account": {
      "id": "109815966467481665",
      "username": "ngstargetbot",
      "acct": "ngstargetbot",
      "display_name": "NGS Content BOT",
      "locked": false,
      "bot": true,
      "discoverable": false,
      "group": false,
      "created_at": "2023-02-06T00:00:00.000Z",
      "note": "<p>TRIAL START</p><p>Automated random toots twice per hour<br />Autoreplies to mentions/replies w/&quot;builds&quot;</p>",
      "url": "https://botsin.space/@ngstargetbot",
      "avatar": "https://files.botsin.space/accounts/avatars/109/815/966/467/481/665/original/aa0b33e3055080b3.png",
      "avatar_static": "https://files.botsin.space/accounts/avatars/109/815/966/467/481/665/original/aa0b33e3055080b3.png",
      "header": "https://files.botsin.space/accounts/headers/109/815/966/467/481/665/original/b53d72ec0b30c92a.jpg",
      "header_static": "https://files.botsin.space/accounts/headers/109/815/966/467/481/665/original/b53d72ec0b30c92a.jpg",
      "followers_count": 5,
      "following_count": 0,
      "statuses_count": 2727,
      "last_status_at": "2023-04-06",
      "noindex": true,
      "emojis": [],
      "roles": [],
      "fields": []
    },
    "media_attachments": [],
    "mentions": [],
    "tags": [],
    "emojis": [],
    "card": null,
    "poll": null
  },
  {
    "id": "110152722539646308",
    "created_at": "2023-04-06T16:05:57.899Z",
    "in_reply_to_id": null,
    "in_reply_to_account_id": null,
    "sensitive": false,
    "spoiler_text": "",
    "visibility": "public",
    "language": "en",
    "uri": "https://botsin.space/users/ngstargetbot/statuses/110152722539646308",
    "url": "https://botsin.space/@ngstargetbot/110152722539646308",
    "replies_count": 0,
    "reblogs_count": 0,
    "favourites_count": 0,
    "edited_at": null,
    "content": "<p>Affix Successful:</p><p>Affix Failed:<br />Fire Exploit IX S 24%<br />Dark Exploit I S 69%<br />Decold Raward 45%<br />Dark Exploit VI 28%<br />Techtech Dualble 40%</p>",
    "reblog": null,
    "application": {
      "name": "CheapBotsTootSweet",
      "website": null
    },
    "account": {
      "id": "109815966467481665",
      "username": "ngstargetbot",
      "acct": "ngstargetbot",
      "display_name": "NGS Content BOT",
      "locked": false,
      "bot": true,
      "discoverable": false,
      "group": false,
      "created_at": "2023-02-06T00:00:00.000Z",
      "note": "<p>TRIAL START</p><p>Automated random toots twice per hour<br />Autoreplies to mentions/replies w/&quot;builds&quot;</p>",
      "url": "https://botsin.space/@ngstargetbot",
      "avatar": "https://files.botsin.space/accounts/avatars/109/815/966/467/481/665/original/aa0b33e3055080b3.png",
      "avatar_static": "https://files.botsin.space/accounts/avatars/109/815/966/467/481/665/original/aa0b33e3055080b3.png",
      "header": "https://files.botsin.space/accounts/headers/109/815/966/467/481/665/original/b53d72ec0b30c92a.jpg",
      "header_static": "https://files.botsin.space/accounts/headers/109/815/966/467/481/665/original/b53d72ec0b30c92a.jpg",
      "followers_count": 5,
      "following_count": 0,
      "statuses_count": 2727,
      "last_status_at": "2023-04-06",
      "noindex": true,
      "emojis": [],
      "roles": [],
      "fields": []
    },
    "media_attachments": [],
    "mentions": [],
    "tags": [],
    "emojis": [],
    "card": null,
    "poll": null
  },
  {
    "id": "110152604495974897",
    "created_at": "2023-04-06T15:35:56.694Z",
    "in_reply_to_id": null,
    "in_reply_to_account_id": null,
    "sensitive": false,
    "spoiler_text": "",
    "visibility": "public",
    "language": "en",
    "uri": "https://botsin.space/users/ngstargetbot/statuses/110152604495974897",
    "url": "https://botsin.space/@ngstargetbot/110152604495974897",
    "replies_count": 0,
    "reblogs_count": 0,
    "favourites_count": 0,
    "edited_at": null,
    "content": "<p>Complex Mineral broken. Obtained the following:<br />Bluefull Chunk<br />Winterlatis<br />Hexalite<br />Mononium<br />Inferno Scale<br />Blizzardcite<br />Icicle Orb</p>",
    "reblog": null,
    "application": {
      "name": "CheapBotsTootSweet",
      "website": null
    },
    "account": {
      "id": "109815966467481665",
      "username": "ngstargetbot",
      "acct": "ngstargetbot",
      "display_name": "NGS Content BOT",
      "locked": false,
      "bot": true,
      "discoverable": false,
      "group": false,
      "created_at": "2023-02-06T00:00:00.000Z",
      "note": "<p>TRIAL START</p><p>Automated random toots twice per hour<br />Autoreplies to mentions/replies w/&quot;builds&quot;</p>",
      "url": "https://botsin.space/@ngstargetbot",
      "avatar": "https://files.botsin.space/accounts/avatars/109/815/966/467/481/665/original/aa0b33e3055080b3.png",
      "avatar_static": "https://files.botsin.space/accounts/avatars/109/815/966/467/481/665/original/aa0b33e3055080b3.png",
      "header": "https://files.botsin.space/accounts/headers/109/815/966/467/481/665/original/b53d72ec0b30c92a.jpg",
      "header_static": "https://files.botsin.space/accounts/headers/109/815/966/467/481/665/original/b53d72ec0b30c92a.jpg",
      "followers_count": 5,
      "following_count": 0,
      "statuses_count": 2727,
      "last_status_at": "2023-04-06",
      "noindex": true,
      "emojis": [],
      "roles": [],
      "fields": []
    },
    "media_attachments": [],
    "mentions": [],
    "tags": [],
    "emojis": [],
    "card": null,
    "poll": null
  },
  {
    "id": "110152486487545715",
    "created_at": "2023-04-06T15:05:56.030Z",
    "in_reply_to_id": null,
    "in_reply_to_account_id": null,
    "sensitive": false,
    "spoiler_text": "",
    "visibility": "public",
    "language": "en",
    "uri": "https://botsin.space/users/ngstargetbot/statuses/110152486487545715",
    "url": "https://botsin.space/@ngstargetbot/110152486487545715",
    "replies_count": 0,
    "reblogs_count": 0,
    "favourites_count": 0,
    "edited_at": null,
    "content": "<p>C/Fire Exploit III S</p>",
    "reblog": null,
    "application": {
      "name": "CheapBotsTootSweet",
      "website": null
    },
    "account": {
      "id": "109815966467481665",
      "username": "ngstargetbot",
      "acct": "ngstargetbot",
      "display_name": "NGS Content BOT",
      "locked": false,
      "bot": true,
      "discoverable": false,
      "group": false,
      "created_at": "2023-02-06T00:00:00.000Z",
      "note": "<p>TRIAL START</p><p>Automated random toots twice per hour<br />Autoreplies to mentions/replies w/&quot;builds&quot;</p>",
      "url": "https://botsin.space/@ngstargetbot",
      "avatar": "https://files.botsin.space/accounts/avatars/109/815/966/467/481/665/original/aa0b33e3055080b3.png",
      "avatar_static": "https://files.botsin.space/accounts/avatars/109/815/966/467/481/665/original/aa0b33e3055080b3.png",
      "header": "https://files.botsin.space/accounts/headers/109/815/966/467/481/665/original/b53d72ec0b30c92a.jpg",
      "header_static": "https://files.botsin.space/accounts/headers/109/815/966/467/481/665/original/b53d72ec0b30c92a.jpg",
      "followers_count": 5,
      "following_count": 0,
      "statuses_count": 2727,
      "last_status_at": "2023-04-06",
      "noindex": true,
      "emojis": [],
      "roles": [],
      "fields": []
    },
    "media_attachments": [],
    "mentions": [],
    "tags": [],
    "emojis": [],
    "card": null,
    "poll": null
  },
  {
    "id": "110152368669124500",
    "created_at": "2023-04-06T14:35:58.261Z",
    "in_reply_to_id": null,
    "in_reply_to_account_id": null,
    "sensitive": false,
    "spoiler_text": "",
    "visibility": "public",
    "language": "en",
    "uri": "https://botsin.space/users/ngstargetbot/statuses/110152368669124500",
    "url": "https://botsin.space/@ngstargetbot/110152368669124500",
    "replies_count": 0,
    "reblogs_count": 0,
    "favourites_count": 0,
    "edited_at": null,
    "content": "<p>Lv.85 Meldrum<br />Weakness: Ilma</p>",
    "reblog": null,
    "application": {
      "name": "CheapBotsTootSweet",
      "website": null
    },
    "account": {
      "id": "109815966467481665",
      "username": "ngstargetbot",
      "acct": "ngstargetbot",
      "display_name": "NGS Content BOT",
      "locked": false,
      "bot": true,
      "discoverable": false,
      "group": false,
      "created_at": "2023-02-06T00:00:00.000Z",
      "note": "<p>TRIAL START</p><p>Automated random toots twice per hour<br />Autoreplies to mentions/replies w/&quot;builds&quot;</p>",
      "url": "https://botsin.space/@ngstargetbot",
      "avatar": "https://files.botsin.space/accounts/avatars/109/815/966/467/481/665/original/aa0b33e3055080b3.png",
      "avatar_static": "https://files.botsin.space/accounts/avatars/109/815/966/467/481/665/original/aa0b33e3055080b3.png",
      "header": "https://files.botsin.space/accounts/headers/109/815/966/467/481/665/original/b53d72ec0b30c92a.jpg",
      "header_static": "https://files.botsin.space/accounts/headers/109/815/966/467/481/665/original/b53d72ec0b30c92a.jpg",
      "followers_count": 5,
      "following_count": 0,
      "statuses_count": 2727,
      "last_status_at": "2023-04-06",
      "noindex": true,
      "emojis": [],
      "roles": [],
      "fields": []
    },
    "media_attachments": [],
    "mentions": [],
    "tags": [],
    "emojis": [],
    "card": null,
    "poll": null
  },
  {
    "id": "110152250636897394",
    "created_at": "2023-04-06T14:05:57.236Z",
    "in_reply_to_id": null,
    "in_reply_to_account_id": null,
    "sensitive": false,
    "spoiler_text": "",
    "visibility": "public",
    "language": "en",
    "uri": "https://botsin.space/users/ngstargetbot/statuses/110152250636897394",
    "url": "https://botsin.space/@ngstargetbot/110152250636897394",
    "replies_count": 0,
    "reblogs_count": 0,
    "favourites_count": 0,
    "edited_at": null,
    "content": "<p>Lv.5 Silver Sweeping Bigg Pliable Gororon<br />Immune: Wires</p>",
    "reblog": null,
    "application": {
      "name": "CheapBotsTootSweet",
      "website": null
    },
    "account": {
      "id": "109815966467481665",
      "username": "ngstargetbot",
      "acct": "ngstargetbot",
      "display_name": "NGS Content BOT",
      "locked": false,
      "bot": true,
      "discoverable": false,
      "group": false,
      "created_at": "2023-02-06T00:00:00.000Z",
      "note": "<p>TRIAL START</p><p>Automated random toots twice per hour<br />Autoreplies to mentions/replies w/&quot;builds&quot;</p>",
      "url": "https://botsin.space/@ngstargetbot",
      "avatar": "https://files.botsin.space/accounts/avatars/109/815/966/467/481/665/original/aa0b33e3055080b3.png",
      "avatar_static": "https://files.botsin.space/accounts/avatars/109/815/966/467/481/665/original/aa0b33e3055080b3.png",
      "header": "https://files.botsin.space/accounts/headers/109/815/966/467/481/665/original/b53d72ec0b30c92a.jpg",
      "header_static": "https://files.botsin.space/accounts/headers/109/815/966/467/481/665/original/b53d72ec0b30c92a.jpg",
      "followers_count": 5,
      "following_count": 0,
      "statuses_count": 2727,
      "last_status_at": "2023-04-06",
      "noindex": true,
      "emojis": [],
      "roles": [],
      "fields": []
    },
    "media_attachments": [],
    "mentions": [],
    "tags": [],
    "emojis": [],
    "card": null,
    "poll": null
  },
  {
    "id": "110152132584015849",
    "created_at": "2023-04-06T13:35:55.892Z",
    "in_reply_to_id": null,
    "in_reply_to_account_id": null,
    "sensitive": false,
    "spoiler_text": "",
    "visibility": "public",
    "language": "en",
    "uri": "https://botsin.space/users/ngstargetbot/statuses/110152132584015849",
    "url": "https://botsin.space/@ngstargetbot/110152132584015849",
    "replies_count": 0,
    "reblogs_count": 0,
    "favourites_count": 0,
    "edited_at": null,
    "content": "<p>Defend Aelio for Beginners 009 from Kelkundo!</p>",
    "reblog": null,
    "application": {
      "name": "CheapBotsTootSweet",
      "website": null
    },
    "account": {
      "id": "109815966467481665",
      "username": "ngstargetbot",
      "acct": "ngstargetbot",
      "display_name": "NGS Content BOT",
      "locked": false,
      "bot": true,
      "discoverable": false,
      "group": false,
      "created_at": "2023-02-06T00:00:00.000Z",
      "note": "<p>TRIAL START</p><p>Automated random toots twice per hour<br />Autoreplies to mentions/replies w/&quot;builds&quot;</p>",
      "url": "https://botsin.space/@ngstargetbot",
      "avatar": "https://files.botsin.space/accounts/avatars/109/815/966/467/481/665/original/aa0b33e3055080b3.png",
      "avatar_static": "https://files.botsin.space/accounts/avatars/109/815/966/467/481/665/original/aa0b33e3055080b3.png",
      "header": "https://files.botsin.space/accounts/headers/109/815/966/467/481/665/original/b53d72ec0b30c92a.jpg",
      "header_static": "https://files.botsin.space/accounts/headers/109/815/966/467/481/665/original/b53d72ec0b30c92a.jpg",
      "followers_count": 5,
      "following_count": 0,
      "statuses_count": 2727,
      "last_status_at": "2023-04-06",
      "noindex": true,
      "emojis": [],
      "roles": [],
      "fields": []
    },
    "media_attachments": [],
    "mentions": [],
    "tags": [],
    "emojis": [],
    "card": null,
    "poll": null
  },
  {
    "id": "110152017559666533",
    "created_at": "2023-04-06T13:06:40.751Z",
    "in_reply_to_id": null,
    "in_reply_to_account_id": null,
    "sensitive": false,
    "spoiler_text": "",
    "visibility": "public",
    "language": "en",
    "uri": "https://botsin.space/users/ngstargetbot/statuses/110152017559666533",
    "url": "https://botsin.space/@ngstargetbot/110152017559666533",
    "replies_count": 0,
    "reblogs_count": 1,
    "favourites_count": 1,
    "edited_at": null,
    "content": "<p>Thank you for your feedback. Here is the response from our developers:</p><p>Quit getting mad at video games</p>",
    "reblog": null,
    "application": {
      "name": "CheapBotsTootSweet",
      "website": null
    },
    "account": {
      "id": "109815966467481665",
      "username": "ngstargetbot",
      "acct": "ngstargetbot",
      "display_name": "NGS Content BOT",
      "locked": false,
      "bot": true,
      "discoverable": false,
      "group": false,
      "created_at": "2023-02-06T00:00:00.000Z",
      "note": "<p>TRIAL START</p><p>Automated random toots twice per hour<br />Autoreplies to mentions/replies w/&quot;builds&quot;</p>",
      "url": "https://botsin.space/@ngstargetbot",
      "avatar": "https://files.botsin.space/accounts/avatars/109/815/966/467/481/665/original/aa0b33e3055080b3.png",
      "avatar_static": "https://files.botsin.space/accounts/avatars/109/815/966/467/481/665/original/aa0b33e3055080b3.png",
      "header": "https://files.botsin.space/accounts/headers/109/815/966/467/481/665/original/b53d72ec0b30c92a.jpg",
      "header_static": "https://files.botsin.space/accounts/headers/109/815/966/467/481/665/original/b53d72ec0b30c92a.jpg",
      "followers_count": 5,
      "following_count": 0,
      "statuses_count": 2727,
      "last_status_at": "2023-04-06",
      "noindex": true,
      "emojis": [],
      "roles": [],
      "fields": []
    },
    "media_attachments": [
      {
        "id": "110152017547891967",
        "type": "image",
        "url": "https://files.botsin.space/media_attachments/files/110/152/017/547/891/967/original/4a44f929b23261be.png",
        "preview_url": "https://files.botsin.space/media_attachments/files/110/152/017/547/891/967/small/4a44f929b23261be.png",
        "remote_url": null,
        "preview_remote_url": null,
        "text_url": null,
        "meta": {
          "original": {
            "width": 1072,
            "height": 603,
            "size": "1072x603",
            "aspect": 1.7777777777777777
          },
          "small": {
            "width": 640,
            "height": 360,
            "size": "640x360",
            "aspect": 1.7777777777777777
          }
        },
        "description": null,
        "blurhash": "UWD9-h?bIUIo~q%gM{M{V?WBoeRk4-IUxus:"
      }
    ],
    "mentions": [],
    "tags": [],
    "emojis": [],
    "card": null,
    "poll": null
  }
]